[{"model": "contenttypes.contenttype", "fields": {"model": "logentry", "app_label": "admin"}, "pk": 1}, {"model": "contenttypes.contenttype", "fields": {"model": "permission", "app_label": "auth"}, "pk": 2}, {"model": "contenttypes.contenttype", "fields": {"model": "group", "app_label": "auth"}, "pk": 3}, {"model": "contenttypes.contenttype", "fields": {"model": "user", "app_label": "auth"}, "pk": 4}, {"model": "contenttypes.contenttype", "fields": {"model": "contenttype", "app_label": "contenttypes"}, "pk": 5}, {"model": "contenttypes.contenttype", "fields": {"model": "session", "app_label": "sessions"}, "pk": 6}, {"model": "contenttypes.contenttype", "fields": {"model": "gcmdevice", "app_label": "push_notifications"}, "pk": 7}, {"model": "contenttypes.contenttype", "fields": {"model": "apnsdevice", "app_label": "push_notifications"}, "pk": 8}, {"model": "contenttypes.contenttype", "fields": {"model": "category", "app_label": "mobapp"}, "pk": 9}, {"model": "contenttypes.contenttype", "fields": {"model": "status", "app_label": "mobapp"}, "pk": 10}, {"model": "contenttypes.contenttype", "fields": {"model": "language", "app_label": "mobapp"}, "pk": 11}, {"model": "contenttypes.contenttype", "fields": {"model": "partner", "app_label": "mobapp"}, "pk": 12}, {"model": "contenttypes.contenttype", "fields": {"model": "dictionaryword", "app_label": "mobapp"}, "pk": 13}, {"model": "mobapp.category", "fields": {"name": "food", "description": "Food vendors"}, "pk": 1}, {"model": "mobapp.category", "fields": {"name": "location", "description": "Location provider"}, "pk": 2}, {"model": "mobapp.category", "fields": {"name": "community", "description": "Community partner"}, "pk": 3}, {"model": "mobapp.category", "fields": {"name": "financial", "description": "Financial support"}, "pk": 4}, {"model": "mobapp.status", "fields": {"name": "active"}, "pk": 1}, {"model": "mobapp.status", "fields": {"name": "pending"}, "pk": 2}, {"model": "mobapp.status", "fields": {"name": "dormant"}, "pk": 3}, {"model": "mobapp.language", "fields": {"name": "english", "language_code": "en", "region": "us"}, "pk": 1}, {"model": "mobapp.language", "fields": {"name": "japanese", "language_code": "jp", "region": "ja"}, "pk": 2}, {"model": "auth.permission", "fields": {"codename": "add_logentry", "name": "Can add log entry", "content_type": 1}, "pk": 1}, {"model": "auth.permission", "fields": {"codename": "change_logentry", "name": "Can change log entry", "content_type": 1}, "pk": 2}, {"model": "auth.permission", "fields": {"codename": "delete_logentry", "name": "Can delete log entry", "content_type": 1}, "pk": 3}, {"model": "auth.permission", "fields": {"codename": "add_permission", "name": "Can add permission", "content_type": 2}, "pk": 4}, {"model": "auth.permission", "fields": {"codename": "change_permission", "name": "Can change permission", "content_type": 2}, "pk": 5}, {"model": "auth.permission", "fields": {"codename": "delete_permission", "name": "Can delete permission", "content_type": 2}, "pk": 6}, {"model": "auth.permission", "fields": {"codename": "add_group", "name": "Can add group", "content_type": 3}, "pk": 7}, {"model": "auth.permission", "fields": {"codename": "change_group", "name": "Can change group", "content_type": 3}, "pk": 8}, {"model": "auth.permission", "fields": {"codename": "delete_group", "name": "Can delete group", "content_type": 3}, "pk": 9}, {"model": "auth.permission", "fields": {"codename": "add_user", "name": "Can add user", "content_type": 4}, "pk": 10}, {"model": "auth.permission", "fields": {"codename": "change_user", "name": "Can change user", "content_type": 4}, "pk": 11}, {"model": "auth.permission", "fields": {"codename": "delete_user", "name": "Can delete user", "content_type": 4}, "pk": 12}, {"model": "auth.permission", "fields": {"codename": "add_contenttype", "name": "Can add content type", "content_type": 5}, "pk": 13}, {"model": "auth.permission", "fields": {"codename": "change_contenttype", "name": "Can change content type", "content_type": 5}, "pk": 14}, {"model": "auth.permission", "fields": {"codename": "delete_contenttype", "name": "Can delete content type", "content_type": 5}, "pk": 15}, {"model": "auth.permission", "fields": {"codename": "add_session", "name": "Can add session", "content_type": 6}, "pk": 16}, {"model": "auth.permission", "fields": {"codename": "change_session", "name": "Can change session", "content_type": 6}, "pk": 17}, {"model": "auth.permission", "fields": {"codename": "delete_session", "name": "Can delete session", "content_type": 6}, "pk": 18}, {"model": "auth.permission", "fields": {"codename": "add_gcmdevice", "name": "Can add GCM device", "content_type": 7}, "pk": 19}, {"model": "auth.permission", "fields": {"codename": "change_gcmdevice", "name": "Can change GCM device", "content_type": 7}, "pk": 20}, {"model": "auth.permission", "fields": {"codename": "delete_gcmdevice", "name": "Can delete GCM device", "content_type": 7}, "pk": 21}, {"model": "auth.permission", "fields": {"codename": "add_apnsdevice", "name": "Can add APNS device", "content_type": 8}, "pk": 22}, {"model": "auth.permission", "fields": {"codename": "change_apnsdevice", "name": "Can change APNS device", "content_type": 8}, "pk": 23}, {"model": "auth.permission", "fields": {"codename": "delete_apnsdevice", "name": "Can delete APNS device", "content_type": 8}, "pk": 24}, {"model": "auth.permission", "fields": {"codename": "add_category", "name": "Can add category", "content_type": 9}, "pk": 25}, {"model": "auth.permission", "fields": {"codename": "change_category", "name": "Can change category", "content_type": 9}, "pk": 26}, {"model": "auth.permission", "fields": {"codename": "delete_category", "name": "Can delete category", "content_type": 9}, "pk": 27}, {"model": "auth.permission", "fields": {"codename": "add_status", "name": "Can add status", "content_type": 10}, "pk": 28}, {"model": "auth.permission", "fields": {"codename": "change_status", "name": "Can change status", "content_type": 10}, "pk": 29}, {"model": "auth.permission", "fields": {"codename": "delete_status", "name": "Can delete status", "content_type": 10}, "pk": 30}, {"model": "auth.permission", "fields": {"codename": "add_language", "name": "Can add language", "content_type": 11}, "pk": 31}, {"model": "auth.permission", "fields": {"codename": "change_language", "name": "Can change language", "content_type": 11}, "pk": 32}, {"model": "auth.permission", "fields": {"codename": "delete_language", "name": "Can delete language", "content_type": 11}, "pk": 33}, {"model": "auth.permission", "fields": {"codename": "add_partner", "name": "Can add partner", "content_type": 12}, "pk": 34}, {"model": "auth.permission", "fields": {"codename": "change_partner", "name": "Can change partner", "content_type": 12}, "pk": 35}, {"model": "auth.permission", "fields": {"codename": "delete_partner", "name": "Can delete partner", "content_type": 12}, "pk": 36}, {"model": "auth.permission", "fields": {"codename": "add_dictionaryword", "name": "Can add dictionary word", "content_type": 13}, "pk": 37}, {"model": "auth.permission", "fields": {"codename": "change_dictionaryword", "name": "Can change dictionary word", "content_type": 13}, "pk": 38}, {"model": "auth.permission", "fields": {"codename": "delete_dictionaryword", "name": "Can delete dictionary word", "content_type": 13}, "pk": 39}, {"model": "auth.user", "fields": {"username": "wyan", "groups": [], "is_staff": true, "last_login": null, "user_permissions": [], "date_joined": "2016-06-01T00:16:44.014Z", "is_superuser": true, "email": "wyan@futomen.net", "last_name": "", "first_name": "", "password": "pbkdf2_sha256$20000$BRntdHZpUsrG$MpYMU6wu7yTzncIzv809uP/esmltkx5xbxpIu88Jnag=", "is_active": true}, "pk": 1}]
