[{"pk": 1, "model": "mobapp.contactinfo", "fields": {"phone": "415-346-2222", "country": "United States", "state": "CA", "postal": "94109", "city": "San Francisco", "street_number": "1161 Post St"}}, {"pk": 1, "model": "mobapp.partner", "fields": {"imageUrl": null, "modificationDate": "2016-06-01T01:23:47Z", "shortDescription_jp": "", "description_jp": "", "name": "Kinokuniya", "category": 2, "name_jp": "", "shortDescription": "Kinokuniya Bookstore", "latitude": 37.785046, "longitude": -122.432281, "contact": null, "description": "Japanese Bookstore\\nThe Osaka festival is located on the 2nd floor of the Kinokuniya building.", "url": null}}, {"pk": 2, "model": "mobapp.partner", "fields": {"imageUrl": "http://www.yamasho-sf.com/images/yamasho_logo_blk.jpg", "modificationDate": "2016-07-14T16:22:57Z", "shortDescription_jp": "\u65e5\u672c\u6599\u7406", "description_jp": "\u65e5\u672c\u6599\u7406\u3068\u30ab\u30e9\u30aa\u30b1\u30ec\u30b9\u30c8\u30e9\u30f3", "name": "Yamasho", "category": 1, "name_jp": "\u5c71\u660c", "shortDescription": "Japanese Restaurant from Osaka", "latitude": 37.7865492, "longitude": -122.4210765, "contact": 1, "description": "Japanese Restaurant\\nShogo Yamada is from Osaka and is glad to help sponsor our event", "url": "http://www.yamasho-sf.com/"}}, {"pk": 3, "model": "mobapp.partner", "fields": {"imageUrl": null, "modificationDate": "2016-06-15T03:31:27Z", "shortDescription_jp": "\u30e8\u30b7\u541b\u306e\u4ed5\u4e8b", "description_jp": "\u306a\u3093\u3068\u304b", "name": "Consulate General of Japan", "category": 3, "name_jp": "\u65e5\u672c\u306e\u9818\u4e8b\u9928", "shortDescription": "The place where Yoshi works", "latitude": 37.7938437, "longitude": -122.4026511, "contact": null, "description": "Community and organizational coordination", "url": null}}]